cycleformers/__init__.py
cycleformers/cycle_trainer.py
cycleformers/cycle_training_arguments.py
cycleformers/data_config.py
cycleformers/model_config.py
cycleformers/trainer_callback.py
cycleformers/types.py
cycleformers/utils.py
cycleformers-0.1.0.dist-info/METADATA
cycleformers-0.1.0.dist-info/WHEEL
cycleformers-0.1.0.dist-info/RECORD
