Metadata-Version: 2.1
Name: cycleformers
Version: 0.1.0
Summary: A comprehensive implementation of the cycle-consistency training paradigm, extending the Huggingface Transformers trainer API to accommodate arbitrary combinations of generative models.
License: Attribution 4.0 International
Author: William Thorne
Author-email: wthorne1@sheffield.ac.uk
Requires-Python: >=3.11,<3.13
Classifier: License :: Other/Proprietary License
Classifier: Programming Language :: Python :: 3
Classifier: Programming Language :: Python :: 3.11
Classifier: Programming Language :: Python :: 3.12
Requires-Dist: datasets (>=3.0.2,<4.0.0)
Requires-Dist: peft (>=0.13.2,<0.14.0)
Requires-Dist: torch (>=2.5.0,<3.0.0)
Requires-Dist: transformers (>=4.46.1,<5.0.0)
Requires-Dist: typing-extensions (>=4.12.2,<5.0.0) ; python_version >= "3.8" and python_version < "3.12"
